hipsnp/__init__.py
hipsnp/_version.py
hipsnp/hipsnp.py
hipsnp/tests/__init__.py
hipsnp/tests/test_genotype.py
hipsnp/tests/test_io.py
hipsnp/utils/__init__.py
hipsnp/utils/logging.py
hipsnp/utils/qctool.py
hipsnp/utils/testing.py
hipsnp-0.0.2.dist-info/AUTHORS.rst
hipsnp-0.0.2.dist-info/LICENSE.md
hipsnp-0.0.2.dist-info/METADATA
hipsnp-0.0.2.dist-info/WHEEL
hipsnp-0.0.2.dist-info/top_level.txt
hipsnp-0.0.2.dist-info/RECORD
