Metadata-Version: 2.1
Name: hipsnp
Version: 0.0.2
Summary: FZJ AML hipsnp library
Home-page: http://juaml.github.io/hipsnp/
Author: Kaustubh Patil
Author-email: k.patil@fz-juelich.de
License: UNKNOWN
Download-URL: https://github.com/juaml/hipsnp/
Project-URL: Documentation, http://juaml.github.io/hipsnp/
Project-URL: Source, https://github.com/juaml/hipsnp/
Project-URL: Tracker, https://github.com/juaml/hipsnp/issues/
Platform: UNKNOWN
Classifier: Intended Audience :: Science/Research
Classifier: Intended Audience :: Developers
Classifier: License :: OSI Approved
Classifier: Programming Language :: Python
Classifier: Topic :: Software Development
Classifier: Topic :: Scientific/Engineering
Classifier: Operating System :: Microsoft :: Windows
Classifier: Operating System :: POSIX
Classifier: Operating System :: Unix
Classifier: Operating System :: MacOS
Classifier: Programming Language :: Python :: 3
Requires-Python: >=3.6
License-File: LICENSE.md
License-File: AUTHORS.rst
Requires-Dist: datalad (>=0.14.0)
Requires-Dist: pandas (>=1.1.2)
Requires-Dist: numpy (>=1.16)
Requires-Dist: bgen-reader (>=4.0.8)
